[{"id":1,"title":"2025-05-12_185247-sinusoidal_equation.pdf"},{"id":2,"title":"2025-04-16-findSinusoidal.pdf"},{"id":3,"title":"2025-04-15-explanationSinus.pdf"},{"id":4,"title":"2025-04-02-PREPA-ES-radians.pdf"},{"id":5,"title":"2025-04-01-EF-corrige-radians.pdf"},{"id":6,"title":"2025-03-24-fonctionsTrigono.pdf"},{"id":7,"title":"2025-03-18-formulas.pdf"},{"id":8,"title":"2025-02-12-particularValues.pdf"},{"id":9,"title":"2025-02-11-arc.pdf"},{"id":10,"title":"2025-01-30-radians.pdf"},{"id":11,"title":"2025-01-29-cercleTrigonometriqueRappel.pdf"},{"id":12,"title":"2025-01-14-prepaESgeoVect_annotated.pdf"},{"id":13,"title":"2025-01-07-alkashi_annotated.pdf"},{"id":14,"title":"2024-12-03-produitScalaireRepereO.pdf"},{"id":15,"title":"2024-12-03-produitScalaireRepereO_annotated.pdf"},{"id":16,"title":"2024-11-27-travail-produitScalaire.pdf"},{"id":17,"title":"2024-11-27-travail-produitScalaireCORR.pdf"},{"id":18,"title":"2024-11-06-produitScalaireParalCORR.pdf"},{"id":19,"title":"2024-11-05-travailphysiqueCORR.pdf"}]
